[{"word": "Emily", "start": 0.106, "end": 0.578}, {"word": "and", "start": 0.592, "end": 0.744}, {"word": "Anna", "start": 0.758, "end": 1.022}, {"word": "go", "start": 1.036, "end": 1.217}, {"word": "to", "start": 1.231, "end": 1.342}, {"word": "the", "start": 1.356, "end": 1.453}, {"word": "market", "start": 1.467, "end": 1.842}, {"word": "early", "start": 1.856, "end": 2.369}, {"word": "Emily", "start": 3.333, "end": 3.792}, {"word": "have", "start": 3.806, "end": 3.958}, {"word": "a", "start": 3.972, "end": 4.042}, {"word": "small", "start": 4.056, "end": 4.403}, {"word": "thing", "start": 4.417, "end": 4.653}, {"word": "with", "start": 4.667, "end": 4.833}, {"word": "money", "start": 4.847, "end": 5.347}, {"word": "Emily", "start": 6.306, "end": 6.792}, {"word": "also", "start": 6.806, "end": 7.153}, {"word": "have", "start": 7.167, "end": 7.333}, {"word": "a", "start": 7.347, "end": 7.417}, {"word": "plan", "start": 7.431, "end": 7.722}, {"word": "of", "start": 7.736, "end": 7.819}, {"word": "thing", "start": 7.833, "end": 8.292}, {"word": "Anna", "start": 9.25, "end": 9.556}, {"word": "point", "start": 9.569, "end": 9.903}, {"word": "to", "start": 9.917, "end": 10.028}, {"word": "a", "start": 10.042, "end": 10.111}, {"word": "shop", "start": 10.125, "end": 10.472}, {"word": "with", "start": 10.486, "end": 10.625}, {"word": "good", "start": 10.639, "end": 10.861}, {"word": "things", "start": 10.875, "end": 11.528}, {"word": "A", "start": 12.486, "end": 12.639}, {"word": "big", "start": 12.653, "end": 12.903}, {"word": "thing", "start": 12.917, "end": 13.167}, {"word": "make", "start": 13.181, "end": 13.389}, {"word": "them", "start": 13.403, "end": 13.583}, {"word": "look", "start": 13.597, "end": 14.028}, {"word": "The", "start": 14.986, "end": 15.125}, {"word": "people", "start": 15.139, "end": 15.5}, {"word": "move", "start": 15.514, "end": 15.708}, {"word": "forward", "start": 15.722, "end": 16.347}, {"word": "Emily", "start": 17.306, "end": 17.722}, {"word": "get", "start": 17.736, "end": 17.903}, {"word": "away", "start": 17.917, "end": 18.167}, {"word": "from", "start": 18.181, "end": 18.361}, {"word": "Anna", "start": 18.375, "end": 18.625}, {"word": "near", "start": 18.639, "end": 18.861}, {"word": "main", "start": 18.875, "end": 19.125}, {"word": "place", "start": 19.139, "end": 19.778}, {"word": "Emily", "start": 20.736, "end": 21.125}, {"word": "feel", "start": 21.139, "end": 21.403}, {"word": "bad", "start": 21.417, "end": 21.806}, {"word": "because", "start": 21.819, "end": 22.153}, {"word": "she", "start": 22.167, "end": 22.306}, {"word": "not", "start": 22.319, "end": 22.569}, {"word": "see", "start": 22.583, "end": 22.778}, {"word": "Anna", "start": 22.792, "end": 23.222}, {"word": "Emily", "start": 24.181, "end": 24.597}, {"word": "look", "start": 24.611, "end": 24.833}, {"word": "around", "start": 24.847, "end": 25.292}, {"word": "and", "start": 25.306, "end": 25.444}, {"word": "try", "start": 25.458, "end": 25.681}, {"word": "to", "start": 25.694, "end": 25.806}, {"word": "know", "start": 25.819, "end": 26.014}, {"word": "way", "start": 26.028, "end": 26.431}, {"word": "Emily", "start": 27.389, "end": 27.792}, {"word": "hope", "start": 27.806, "end": 28.028}, {"word": "to", "start": 28.042, "end": 28.125}, {"word": "hear", "start": 28.139, "end": 28.431}, {"word": "Anna", "start": 28.444, "end": 28.681}, {"word": "call", "start": 28.694, "end": 28.972}, {"word": "name", "start": 28.986, "end": 29.375}, {"word": "A", "start": 30.333, "end": 30.486}, {"word": "kind", "start": 30.5, "end": 30.861}, {"word": "woman", "start": 30.875, "end": 31.194}, {"word": "near", "start": 31.208, "end": 31.403}, {"word": "walk", "start": 31.417, "end": 31.694}, {"word": "see", "start": 31.708, "end": 31.903}, {"word": "Emily", "start": 31.917, "end": 32.556}, {"word": "She", "start": 33.514, "end": 33.75}, {"word": "see", "start": 33.764, "end": 33.972}, {"word": "Emily", "start": 33.986, "end": 34.417}, {"word": "feel", "start": 34.431, "end": 34.722}, {"word": "bad", "start": 34.736, "end": 35.194}, {"word": "She", "start": 36.153, "end": 36.417}, {"word": "ask", "start": 36.431, "end": 36.736}, {"word": "if", "start": 36.75, "end": 36.861}, {"word": "Emily", "start": 36.875, "end": 37.236}, {"word": "need", "start": 37.25, "end": 37.472}, {"word": "help", "start": 37.486, "end": 37.944}, {"word": "She", "start": 38.903, "end": 39.139}, {"word": "say", "start": 39.153, "end": 39.375}, {"word": "she", "start": 39.389, "end": 39.556}, {"word": "will", "start": 39.569, "end": 39.736}, {"word": "lead", "start": 39.75, "end": 39.944}, {"word": "to", "start": 39.958, "end": 40.056}, {"word": "information", "start": 40.069, "end": 40.708}, {"word": "office", "start": 40.722, "end": 41.375}, {"word": "The", "start": 42.333, "end": 42.458}, {"word": "information", "start": 42.472, "end": 43.153}, {"word": "office", "start": 43.167, "end": 43.542}, {"word": "have", "start": 43.556, "end": 43.694}, {"word": "a", "start": 43.708, "end": 43.778}, {"word": "staff", "start": 43.792, "end": 44.486}, {"word": "The", "start": 45.444, "end": 45.597}, {"word": "staff", "start": 45.611, "end": 45.944}, {"word": "say", "start": 45.958, "end": 46.222}, {"word": "and", "start": 46.236, "end": 46.375}, {"word": "give", "start": 46.389, "end": 46.583}, {"word": "map", "start": 46.597, "end": 47.069}, {"word": "The", "start": 48.028, "end": 48.167}, {"word": "map", "start": 48.181, "end": 48.458}, {"word": "show", "start": 48.472, "end": 48.667}, {"word": "way", "start": 48.681, "end": 48.833}, {"word": "to", "start": 48.847, "end": 48.972}, {"word": "shop", "start": 48.986, "end": 49.528}, {"word": "The", "start": 50.486, "end": 50.625}, {"word": "map", "start": 50.639, "end": 50.944}, {"word": "help", "start": 50.958, "end": 51.167}, {"word": "Emily", "start": 51.181, "end": 51.528}, {"word": "find", "start": 51.542, "end": 51.875}, {"word": "Anna", "start": 51.889, "end": 52.333}, {"word": "Emily", "start": 53.292, "end": 53.708}, {"word": "go", "start": 53.722, "end": 53.889}, {"word": "to", "start": 53.903, "end": 54.014}, {"word": "shop", "start": 54.028, "end": 54.486}, {"word": "but", "start": 54.5, "end": 54.639}, {"word": "people", "start": 54.653, "end": 54.958}, {"word": "stay", "start": 54.972, "end": 55.222}, {"word": "line", "start": 55.236, "end": 55.764}, {"word": "Emily", "start": 56.722, "end": 57.181}, {"word": "ask", "start": 57.194, "end": 57.5}, {"word": "shop", "start": 57.514, "end": 57.806}, {"word": "person", "start": 57.819, "end": 58.264}, {"word": "for", "start": 58.278, "end": 58.444}, {"word": "another", "start": 58.458, "end": 58.806}, {"word": "route", "start": 58.819, "end": 59.306}, {"word": "The", "start": 60.264, "end": 60.403}, {"word": "shop", "start": 60.417, "end": 60.736}, {"word": "person", "start": 60.75, "end": 61.153}, {"word": "say", "start": 61.167, "end": 61.361}, {"word": "yes", "start": 61.375, "end": 61.667}, {"word": "side", "start": 61.681, "end": 61.958}, {"word": "place", "start": 61.972, "end": 62.597}, {"word": "The", "start": 63.556, "end": 63.708}, {"word": "side", "start": 63.722, "end": 64.056}, {"word": "place", "start": 64.069, "end": 64.403}, {"word": "go", "start": 64.417, "end": 64.569}, {"word": "around", "start": 64.583, "end": 64.944}, {"word": "people", "start": 64.958, "end": 65.514}, {"word": "The", "start": 66.472, "end": 66.611}, {"word": "map", "start": 66.625, "end": 66.903}, {"word": "show", "start": 66.917, "end": 67.139}, {"word": "side", "start": 67.153, "end": 67.486}, {"word": "place", "start": 67.5, "end": 67.806}, {"word": "go", "start": 67.819, "end": 67.958}, {"word": "to", "start": 67.972, "end": 68.083}, {"word": "shop", "start": 68.097, "end": 68.639}, {"word": "Emily", "start": 69.597, "end": 70.0}, {"word": "go", "start": 70.014, "end": 70.181}, {"word": "to", "start": 70.194, "end": 70.306}, {"word": "shop", "start": 70.319, "end": 70.653}, {"word": "and", "start": 70.667, "end": 70.806}, {"word": "see", "start": 70.819, "end": 71.028}, {"word": "Anna", "start": 71.042, "end": 71.472}, {"word": "Anna", "start": 72.431, "end": 72.722}, {"word": "good", "start": 72.736, "end": 72.944}, {"word": "and", "start": 72.958, "end": 73.083}, {"word": "run", "start": 73.097, "end": 73.319}, {"word": "to", "start": 73.333, "end": 73.431}, {"word": "Emily", "start": 73.444, "end": 74.069}, {"word": "They", "start": 75.028, "end": 75.181}, {"word": "hold", "start": 75.194, "end": 75.486}, {"word": "each", "start": 75.5, "end": 75.667}, {"word": "other", "start": 75.681, "end": 76.125}, {"word": "The", "start": 77.083, "end": 77.236}, {"word": "kind", "start": 77.25, "end": 77.597}, {"word": "woman", "start": 77.611, "end": 77.944}, {"word": "watch", "start": 77.958, "end": 78.306}, {"word": "them", "start": 78.319, "end": 78.708}, {"word": "Emily", "start": 79.667, "end": 80.097}, {"word": "say", "start": 80.111, "end": 80.361}, {"word": "thank", "start": 80.375, "end": 80.736}, {"word": "and", "start": 80.75, "end": 80.833}, {"word": "be", "start": 80.847, "end": 80.986}, {"word": "good", "start": 81.0, "end": 81.458}, {"word": "The", "start": 82.417, "end": 82.556}, {"word": "market", "start": 82.569, "end": 83.028}, {"word": "have", "start": 83.042, "end": 83.208}, {"word": "many", "start": 83.222, "end": 83.528}, {"word": "little", "start": 83.542, "end": 83.833}, {"word": "lines", "start": 83.847, "end": 84.528}, {"word": "The", "start": 85.486, "end": 85.653}, {"word": "lines", "start": 85.667, "end": 86.056}, {"word": "turn", "start": 86.069, "end": 86.347}, {"word": "between", "start": 86.361, "end": 86.736}, {"word": "big", "start": 86.75, "end": 86.986}, {"word": "shops", "start": 87.0, "end": 87.681}, {"word": "Sign", "start": 88.639, "end": 89.014}, {"word": "help", "start": 89.028, "end": 89.222}, {"word": "people", "start": 89.236, "end": 89.542}, {"word": "find", "start": 89.556, "end": 89.861}, {"word": "places", "start": 89.875, "end": 90.639}, {"word": "The", "start": 91.597, "end": 91.722}, {"word": "information", "start": 91.736, "end": 92.444}, {"word": "office", "start": 92.458, "end": 92.792}, {"word": "sit", "start": 92.806, "end": 93.069}, {"word": "near", "start": 93.083, "end": 93.264}, {"word": "main", "start": 93.278, "end": 93.528}, {"word": "place", "start": 93.542, "end": 94.208}, {"word": "Lucy", "start": 95.167, "end": 95.583}, {"word": "work", "start": 95.597, "end": 95.861}, {"word": "at", "start": 95.875, "end": 95.958}, {"word": "the", "start": 95.972, "end": 96.056}, {"word": "information", "start": 96.069, "end": 96.708}, {"word": "office", "start": 96.722, "end": 97.375}, {"word": "Lucy", "start": 98.333, "end": 98.764}, {"word": "say", "start": 98.778, "end": 99.014}, {"word": "she", "start": 99.028, "end": 99.222}, {"word": "like", "start": 99.236, "end": 99.458}, {"word": "give", "start": 99.472, "end": 99.653}, {"word": "good", "start": 99.667, "end": 99.875}, {"word": "way", "start": 99.889, "end": 100.278}, {"word": "The", "start": 101.236, "end": 101.389}, {"word": "staff", "start": 101.403, "end": 101.722}, {"word": "train", "start": 101.736, "end": 102.083}, {"word": "to", "start": 102.097, "end": 102.208}, {"word": "answer", "start": 102.222, "end": 102.569}, {"word": "questions", "start": 102.583, "end": 103.444}, {"word": "Emily", "start": 104.403, "end": 104.819}, {"word": "thank", "start": 104.833, "end": 105.111}, {"word": "staff", "start": 105.125, "end": 105.514}, {"word": "and", "start": 105.528, "end": 105.681}, {"word": "say", "start": 105.694, "end": 105.889}, {"word": "tell", "start": 105.903, "end": 106.194}, {"word": "others", "start": 106.208, "end": 106.806}, {"word": "Emily", "start": 107.764, "end": 108.208}, {"word": "say", "start": 108.222, "end": 108.5}, {"word": "she", "start": 108.514, "end": 108.708}, {"word": "will", "start": 108.722, "end": 108.861}, {"word": "bring", "start": 108.875, "end": 109.125}, {"word": "friend", "start": 109.139, "end": 109.542}, {"word": "next", "start": 109.556, "end": 109.889}, {"word": "time", "start": 109.903, "end": 110.389}, {"word": "The", "start": 111.347, "end": 111.5}, {"word": "story", "start": 111.514, "end": 111.847}, {"word": "show", "start": 111.861, "end": 112.111}, {"word": "ask", "start": 112.125, "end": 112.389}, {"word": "for", "start": 112.403, "end": 112.542}, {"word": "help", "start": 112.556, "end": 112.778}, {"word": "is", "start": 112.792, "end": 112.944}, {"word": "good", "start": 112.958, "end": 113.417}, {"word": "stay", "start": 114.375, "end": 114.708}, {"word": "good", "start": 114.722, "end": 115.042}, {"word": "and", "start": 115.056, "end": 115.181}, {"word": "use", "start": 115.194, "end": 115.431}, {"word": "good", "start": 115.444, "end": 115.611}, {"word": "directions", "start": 115.625, "end": 116.528}, {"word": "Emily", "start": 117.486, "end": 117.944}, {"word": "will", "start": 117.958, "end": 118.111}, {"word": "help", "start": 118.125, "end": 118.347}, {"word": "others", "start": 118.361, "end": 118.708}, {"word": "next", "start": 118.722, "end": 119.347}]
